CREDITS
LICENSE
MANIFEST.in
README.rst
dimgx.py
setup.cfg
setup.py
_dimgx/__init__.py
_dimgx/cmd.py
_dimgx/version.py
dimgx.egg-info/PKG-INFO
dimgx.egg-info/SOURCES.txt
dimgx.egg-info/dependency_links.txt
dimgx.egg-info/entry_points.txt
dimgx.egg-info/requires.txt
dimgx.egg-info/top_level.txt
doc/CREDITS.rst
doc/LICENSE.rst
doc/cli.rst
doc/conf.py
doc/contrib.rst
doc/index.rst
doc/intro.rst
doc/py.rst
doc/release_checklist.md
doc/requirements.txt
test/__init__.py
test/fauxdockerclient.py
test/requirements.txt
test/test_cmd.py
test/test_dimgx.py
test/data/05883322010f/layer.tar
test/data/0ab95943010e/layer.tar
test/data/0c2ccea2000a/layer.tar
test/data/149dccab0003/layer.tar
test/data/20767f420106/layer.tar
test/data/2a6fd83c010c/layer.tar
test/data/2b32db6c0000/layer.tar
test/data/2e7523f2000d/layer.tar
test/data/37c550ef0108/layer.tar
test/data/3807f4cc0006/layer.tar
test/data/424b1d5a0009/layer.tar
test/data/433d6bca0107/layer.tar
test/data/477a2fc6010b/layer.tar
test/data/483619750007/layer.tar
test/data/4fd6a0870104/layer.tar
test/data/52d7263f000f/layer.tar
test/data/5a48f220000e/layer.tar
test/data/7c3c1af8000b/layer.tar
test/data/800c14150100/layer.tar
test/data/91d168b90105/layer.tar
test/data/9c4784350103/layer.tar
test/data/9e42fa970004/layer.tar
test/data/a0d4a0b80101/layer.tar
test/data/c6566e3d0102/layer.tar
test/data/d21db9c2000c/layer.tar
test/data/dd1d42190005/layer.tar
test/data/e0771bbb010d/layer.tar
test/data/e79d00850008/layer.tar
test/data/e97a31f3010a/layer.tar
test/data/ef8adbef0109/layer.tar
test/data/f62dd7680002/layer.tar
test/data/ff304d2a0001/layer.tar