Metadata-Version: 1.1
Name: dimgx
Version: 0.2.4
Summary: Docker IMaGe layer eXtractor (and flattener)
Home-page: https://dimgx.readthedocs.org/en/v0.2.4/
Author: Matt Bogosian
Author-email: matt@bogosian.net
License: MIT License
Platform: UNKNOWN
Classifier: Topic :: Software Development :: Build Tools
Classifier: Development Status :: 4 - Beta
Classifier: Environment :: Console
Classifier: Intended Audience :: Developers
Classifier: License :: OSI Approved :: MIT License
Classifier: Operating System :: OS Independent
Classifier: Programming Language :: Python
Classifier: Programming Language :: Python :: 2.7
Classifier: Programming Language :: Python :: 3.3
Classifier: Programming Language :: Python :: 3.4
Classifier: Programming Language :: Python :: Implementation :: CPython
Classifier: Programming Language :: Python :: Implementation :: PyPy
Classifier: Topic :: System :: Archiving :: Packaging
